{"filename": "3209648408_09-23-1999-CT_UROGRAM-31798_3_000000-PARENCHYMAL_PHASE_Sep1999-95798_1-088.dcm", "annotation": [{"key": {"text": "Institution Name", "bbox": [264, 42, 363, 50]}, "value": {"text": "Nielsen, Jimenez and Aguilar Community Hospital", "bbox": [367, 70, 485, 80]}}, {"key": {"text": "Study Date", "bbox": [264, 84, 331, 94]}, "value": {"text": "1999 Sep 23", "bbox": [335, 85, 405, 94]}}, {"key": {"text": "Patient ID", "bbox": [264, 98, 324, 106]}, "value": {"text": "3209648408", "bbox": [328, 99, 398, 106]}}, {"key": {"text": "Name", "bbox": [264, 113, 300, 120]}, "value": {"text": "SEXTON CARMEN", "bbox": [304, 113, 401, 120]}}, {"key": {"text": "Age", "bbox": [264, 127, 290, 136]}, "value": {"text": "67", "bbox": [294, 127, 308, 134]}}, {"key": {"text": "DOB", "bbox": [264, 141, 292, 148]}, "value": {"text": "08/04/1932", "bbox": [296, 141, 359, 149]}}]}