{"filename": "3209648408_09-23-1999-CT_UROGRAM-31798_3_000000-PARENCHYMAL_PHASE_Sep1999-95798_1-140.dcm", "annotation": [{"key": {"text": "Institution Name", "bbox": [288, 49, 387, 57]}, "value": {"text": "Nielsen, Jimenez and Aguilar Community Hospital", "bbox": [391, 77, 509, 87]}}, {"key": {"text": "Study Date", "bbox": [288, 91, 355, 101]}, "value": {"text": "1999 Sep 23", "bbox": [359, 92, 429, 101]}}, {"key": {"text": "Patient ID", "bbox": [288, 105, 348, 113]}, "value": {"text": "3209648408", "bbox": [352, 106, 422, 113]}}, {"key": {"text": "Name", "bbox": [288, 120, 324, 127]}, "value": {"text": "SEXTON CARMEN", "bbox": [328, 120, 425, 127]}}, {"key": {"text": "Age", "bbox": [288, 134, 314, 143]}, "value": {"text": "67", "bbox": [318, 134, 332, 141]}}, {"key": {"text": "DOB", "bbox": [288, 148, 316, 155]}, "value": {"text": "08/04/1932", "bbox": [320, 148, 383, 156]}}]}