{"filename": "9894340694_04-16-1997-MRI_ABDOMEN_PELVIS_WWO_CONT-87318_6_000000-LIVER-KIDNEYTIFL2DAXIAL-30038_1-07.dcm", "annotation": [{"key": {"text": "Study Date"}, "value": {"text": "1997 Apr 16", "bbox": [40, 201, 75, 206]}}, {"key": {"text": "Name"}, "value": {"text": "MILLER BEVERLY", "bbox": [79, 201, 126, 205]}}, {"key": {"text": "Patient Sex"}, "value": {"text": "F", "bbox": [130, 201, 133, 205]}}, {"key": {"text": "DOB", "bbox": [40, 210, 54, 214]}, "value": {"text": "02/27/1931", "bbox": [58, 210, 90, 214]}}]}