{"filename": "9894340694_04-16-1997-MRI_ABDOMEN_PELVIS_WWO_CONT-87318_16_000000-LIVER-PELVISHASTESAGPOS-74838_1-18.dcm", "annotation": [{"key": {"text": "Study Date"}, "value": {"text": "1997 Apr 16", "bbox": [47, 15, 82, 20]}}, {"key": {"text": "Name"}, "value": {"text": "MILLER BEVERLY", "bbox": [86, 15, 133, 19]}}, {"key": {"text": "Patient Sex"}, "value": {"text": "F", "bbox": [137, 15, 140, 19]}}, {"key": {"text": "DOB", "bbox": [47, 24, 61, 28]}, "value": {"text": "02/27/1931", "bbox": [65, 24, 97, 28]}}]}